polywrap_fs_plugin/__init__.py
polywrap_fs_plugin/py.typed
polywrap_fs_plugin/wrap/__init__.py
polywrap_fs_plugin/wrap/module.py
polywrap_fs_plugin/wrap/types.py
polywrap_fs_plugin/wrap/wrap_info.py
polywrap_fs_plugin-0.1.2.dist-info/METADATA
polywrap_fs_plugin-0.1.2.dist-info/WHEEL
polywrap_fs_plugin-0.1.2.dist-info/RECORD
